README.md
setup.py
./EasyDB/C/cmiscs.c
EasyDB/__init__.py
EasyDB/main.py
EasyDB.py.egg-info/PKG-INFO
EasyDB.py.egg-info/SOURCES.txt
EasyDB.py.egg-info/dependency_links.txt
EasyDB.py.egg-info/top_level.txt
EasyDB/C/__init__.py
EasyDB/bases/__init__.py
EasyDB/bases/ccode.py
EasyDB/bases/classes.py
EasyDB/bases/db.py
EasyDB/bases/decorators.py
EasyDB/bases/functions.py
EasyDB/bases/types.py
EasyDB/collections_/__init__.py
EasyDB/collections_/model.py