Metadata-Version: 2.1
Name: EasyDB.py
Version: 1.2.3
Summary: A very easy database but very good :)
Author: Nando Msc
Project-URL: Home Page, https://github.com/einaidev/EasyDB
Project-URL: GitHub, https://github.com/einaidev
Project-URL: Documentation, https://github.com/einaidev/EasyDB/blob/main/README.md
Keywords: DataBase,DB,Json
Classifier: License :: OSI Approved :: MIT License
Requires: Cython
Requires-Python: >=3.10
